LICENSE
README.md
setup.py
damescipy/runtests.sh
damescipy.egg-info/PKG-INFO
damescipy.egg-info/SOURCES.txt
damescipy.egg-info/dependency_links.txt
damescipy.egg-info/not-zip-safe
damescipy.egg-info/requires.txt
damescipy.egg-info/top_level.txt
damescipy/tests/__init__.py
damescipy/tests/test_basics.py
damescipy/tests/test_pvalues.py
damescipy/tests/test_stats.py