Metadata-Version: 2.1
Name: damescipy
Version: 0.1.2
Summary: Learning Scipy from Tests by David Arroyo Menéndez
Home-page: http://github.com/davidam/damescipy
Author: David Arroyo Menéndez
Author-email: davidam@gmail.com
License: GPLv3
Keywords: scipy tests
Classifier: Development Status :: 3 - Alpha
Classifier: License :: OSI Approved :: GNU General Public License v3 (GPLv3)
Classifier: Programming Language :: Python :: 3.6
Classifier: Topic :: Scientific/Engineering
License-File: LICENSE
